muninn_sentinel5p.py
muninn_sentinel5p-3.1.dist-info/METADATA
muninn_sentinel5p-3.1.dist-info/WHEEL
muninn_sentinel5p-3.1.dist-info/top_level.txt
muninn_sentinel5p-3.1.dist-info/RECORD
