Metadata-Version: 2.1
Name: muninn-sentinel5p
Version: 3.1
Summary: Muninn extension for official L1/L2/AUX Copernicus Sentinel-5P products
Home-page: https://github.com/stcorp/muninn-sentinel5p
Author: S[&]T
Author-email: UNKNOWN
License: BSD
Platform: UNKNOWN
Classifier: Development Status :: 5 - Production/Stable
Classifier: Programming Language :: Python :: 2
Classifier: Programming Language :: Python :: 3
Classifier: License :: OSI Approved :: BSD License
Classifier: Operating System :: OS Independent
Classifier: Topic :: Scientific/Engineering
Classifier: Environment :: Plugins
Requires-Dist: muninn
